setup.py
abcd_distribution/Binomialdistribution.py
abcd_distribution/Gaussiandistribution.py
abcd_distribution/Generaldistribution.py
abcd_distribution/__init__.py
abcd_distribution.egg-info/PKG-INFO
abcd_distribution.egg-info/SOURCES.txt
abcd_distribution.egg-info/dependency_links.txt
abcd_distribution.egg-info/not-zip-safe
abcd_distribution.egg-info/top_level.txt