Metadata-Version: 1.0
Name: abcd-distribution
Version: 0.1
Summary: Gaussian distributions
Home-page: UNKNOWN
Author: Charlie Choong
Author-email: choongjinyao@hotmail.com
License: UNKNOWN
Platform: UNKNOWN
